reblite/__init__.py
reblite/__main__.py
reblite/db.py
reblite/exceptions.py
reblite-1.1.1.dist-info/LICENSE
reblite-1.1.1.dist-info/METADATA
reblite-1.1.1.dist-info/WHEEL
reblite-1.1.1.dist-info/top_level.txt
reblite-1.1.1.dist-info/RECORD
