Metadata-Version: 2.1
Name: reblite
Version: 1.1.1
Summary: A simple SQLite wrapper built for personal use.
Home-page: https://github.com/4041RebL/sqlite-wrapper
Author: Harsh Vardhan
Author-email: vardhan.harsh4041@gmail.com
License: UNKNOWN
Platform: UNKNOWN
Classifier: Programming Language :: Python :: 3
Classifier: License :: OSI Approved :: MIT License
Classifier: Operating System :: OS Independent
Requires-Python: >=3.6
